odoo10_addon_l10n_it_ipa-10.0.1.0.0-py2.7-nspkg.pth
odoo10_addon_l10n_it_ipa-10.0.1.0.0.dist-info/top_level.txt
odoo10_addon_l10n_it_ipa-10.0.1.0.0.dist-info/WHEEL
odoo10_addon_l10n_it_ipa-10.0.1.0.0.dist-info/RECORD
odoo10_addon_l10n_it_ipa-10.0.1.0.0.dist-info/metadata.json
odoo10_addon_l10n_it_ipa-10.0.1.0.0.dist-info/DESCRIPTION.rst
odoo10_addon_l10n_it_ipa-10.0.1.0.0.dist-info/METADATA
odoo10_addon_l10n_it_ipa-10.0.1.0.0.dist-info/namespace_packages.txt
odoo/addons/l10n_it_ipa/__manifest__.py
odoo/addons/l10n_it_ipa/__init__.py
odoo/addons/l10n_it_ipa/README.rst
odoo/addons/l10n_it_ipa/view/partner_view.xml
odoo/addons/l10n_it_ipa/i18n/it.po
odoo/addons/l10n_it_ipa/i18n/es.po
odoo/addons/l10n_it_ipa/i18n/sl.po
odoo/addons/l10n_it_ipa/model/partner.py
odoo/addons/l10n_it_ipa/model/__init__.py
odoo/addons/l10n_it_ipa/static/description/icon.png
